riskroller/__init__.py
riskroller/riskroller.py
riskroller-0.1.5.dist-info/METADATA
riskroller-0.1.5.dist-info/RECORD
riskroller-0.1.5.dist-info/WHEEL
riskroller-0.1.5.dist-info/entry_points.txt
riskroller-0.1.5.dist-info/top_level.txt
