Metadata-Version: 2.1
Name: riskroller
Version: 0.1.5
Summary: Play one random or inputed initial conditions of a round of Risk.
Home-page: https://github.com/Parimer/riskroller
Author: James Campbell
Author-email: james@jamescampbell.us
License: GPLv3
Download-URL: https://github.com/Parimer/riskroller/archive/0.1.5.tar.gz
Keywords: risk,data-analysis,dice,statistics,die-roll
Platform: UNKNOWN
Classifier: Programming Language :: Python :: 3 :: Only
Requires-Dist: argparse
Requires-Dist: setuptools
